{
    "kind": "youtube#commentThreadListResponse",
    "etag": "8qxeyuvNAW824e-hZOIateKfIJI",
    "pageInfo": {
        "totalResults": 13,
        "resultsPerPage": 100
    },
    "items": [
        {
            "kind": "youtube#commentThread",
            "etag": "N2GW0TEeEWl3XsI3aVL2xpZW1Ng",
            "id": "UgzRTLTXb5JB3Lf2zBR4AaABAg",
            "snippet": {
                "channelId": "UCXuO_AmrcE16fDoNiq9JZZg",
                "videoId": "Wm_lx5DJWZE",
                "topLevelComment": {
                    "kind": "youtube#comment",
                    "etag": "k7A2Z1lx1CAt9e8XMI5EJY4Oba0",
                    "id": "UgzRTLTXb5JB3Lf2zBR4AaABAg",
                    "snippet": {
                        "channelId": "UCXuO_AmrcE16fDoNiq9JZZg",
                        "videoId": "Wm_lx5DJWZE",
                        "textDisplay": "When her song comes in my shorts..as \" Mai nahi to kon be....\"\nMe \" bhak be madharch@d...\"",
                        "textOriginal": "When her song comes in my shorts..as \" Mai nahi to kon be....\"\nMe \" bhak be madharch@d...\"",
                        "authorDisplayName": "@sscian_abhinandan",
                        "authorProfileImageUrl": "https://yt3.ggpht.com/R_LnZ_QhB8R5QnU2DFd82qAr7ETDEI8P7Vf-BW7oyywPcbJxXHHS9C8ifUfa_8OzvRHIVDmW=s48-c-k-c0x00ffffff-no-rj",
                        "authorChannelUrl": "http://www.youtube.com/@sscian_abhinandan",
                        "authorChannelId": {
                            "value": "UCf_erEnoNQduEkdhkQc3hHg"
                        },
                        "canRate": true,
                        "viewerRating": "none",
                        "likeCount": 0,
                        "publishedAt": "2024-09-24T04:07:13Z",
                        "updatedAt": "2024-09-24T04:07:13Z"
                    }
                },
                "canReply": true,
                "totalReplyCount": 0,
                "isPublic": true
            }
        },
        {
            "kind": "youtube#commentThread",
            "etag": "Y-mcliWAzmInvUlILxKOtO39JmE",
            "id": "Ugx97vtwF9UpYUUr_HN4AaABAg",
            "snippet": {
                "channelId": "UCXuO_AmrcE16fDoNiq9JZZg",
                "videoId": "Wm_lx5DJWZE",
                "topLevelComment": {
                    "kind": "youtube#comment",
                    "etag": "ssK32BrcWgoRaoWqALEyI9G1SLU",
                    "id": "Ugx97vtwF9UpYUUr_HN4AaABAg",
                    "snippet": {
                        "channelId": "UCXuO_AmrcE16fDoNiq9JZZg",
                        "videoId": "Wm_lx5DJWZE",
                        "textDisplay": "Coke studio kindly bring Tripuri folk song \u2764\u2764\u2764",
                        "textOriginal": "Coke studio kindly bring Tripuri folk song \u2764\u2764\u2764",
                        "authorDisplayName": "@Important11-u5p",
                        "authorProfileImageUrl": "https://yt3.ggpht.com/U0z6ZG1kJm_qDE4rEw3nBjQVlopGdWi07wiBprOBdhgsP2-1eOMnkKlbttoB3DjBjupP4R4gUAI=s48-c-k-c0x00ffffff-no-rj",
                        "authorChannelUrl": "http://www.youtube.com/@Important11-u5p",
                        "authorChannelId": {
                            "value": "UCm6CkHrh4ZCt1tnezPpizFg"
                        },
                        "canRate": true,
                        "viewerRating": "none",
                        "likeCount": 0,
                        "publishedAt": "2024-09-07T02:01:39Z",
                        "updatedAt": "2024-09-07T02:01:39Z"
                    }
                },
                "canReply": true,
                "totalReplyCount": 0,
                "isPublic": true
            }
        },
        {
            "kind": "youtube#commentThread",
            "etag": "uGd-OVtX5w5mbFgva-KTuhdDCBM",
            "id": "UgwDM3JVQkQHdEQ8UFJ4AaABAg",
            "snippet": {
                "channelId": "UCXuO_AmrcE16fDoNiq9JZZg",
                "videoId": "Wm_lx5DJWZE",
                "topLevelComment": {
                    "kind": "youtube#comment",
                    "etag": "DpiB-flNG3GbFRNtNiUcK1C1Tzo",
                    "id": "UgwDM3JVQkQHdEQ8UFJ4AaABAg",
                    "snippet": {
                        "channelId": "UCXuO_AmrcE16fDoNiq9JZZg",
                        "videoId": "Wm_lx5DJWZE",
                        "textDisplay": "But Pakistani Cock Blockbuster nailed \ud83d\udd25 \ud83d\udd25",
                        "textOriginal": "But Pakistani Cock Blockbuster nailed \ud83d\udd25 \ud83d\udd25",
                        "authorDisplayName": "@KBENTERTAINMENTMEDIA",
                        "authorProfileImageUrl": "https://yt3.ggpht.com/4iu4p8u2IOIyi_rlkfO4Wktl_GbORQMnqRqom1I0bsdRYV-jJdGKhcXmq1yEcVaDiovLlimQ=s48-c-k-c0x00ffffff-no-rj",
                        "authorChannelUrl": "http://www.youtube.com/@KBENTERTAINMENTMEDIA",
                        "authorChannelId": {
                            "value": "UCQFXP-hx0gbH0Ik0siksJOg"
                        },
                        "canRate": true,
                        "viewerRating": "none",
                        "likeCount": 0,
                        "publishedAt": "2024-09-02T03:50:20Z",
                        "updatedAt": "2024-09-02T03:50:20Z"
                    }
                },
                "canReply": true,
                "totalReplyCount": 0,
                "isPublic": true
            }
        },
        {
            "kind": "youtube#commentThread",
            "etag": "qBXbXxLig2kkRvU37MdVx3J7Pfc",
            "id": "UgwMvwSdSOLqos4KGBV4AaABAg",
            "snippet": {
                "channelId": "UCXuO_AmrcE16fDoNiq9JZZg",
                "videoId": "Wm_lx5DJWZE",
                "topLevelComment": {
                    "kind": "youtube#comment",
                    "etag": "B_9xaF3s_JI6bUou_uJmRnbOQUk",
                    "id": "UgwMvwSdSOLqos4KGBV4AaABAg",
                    "snippet": {
                        "channelId": "UCXuO_AmrcE16fDoNiq9JZZg",
                        "videoId": "Wm_lx5DJWZE",
                        "textDisplay": "So proud of you Shruti dii \u2764",
                        "textOriginal": "So proud of you Shruti dii \u2764",
                        "authorDisplayName": "@Mechgirl1828",
                        "authorProfileImageUrl": "https://yt3.ggpht.com/31_YSXzRkmhLRqSMRHpw-G2WJ1X8-mgtx5B_KLvN5Fg55SRhrUlCkXkv9B5ITsCraXMdMg7Uqw=s48-c-k-c0x00ffffff-no-rj",
                        "authorChannelUrl": "http://www.youtube.com/@Mechgirl1828",
                        "authorChannelId": {
                            "value": "UCby_Ncyano-FfZKhmMV7mzw"
                        },
                        "canRate": true,
                        "viewerRating": "none",
                        "likeCount": 1,
                        "publishedAt": "2024-09-01T17:56:32Z",
                        "updatedAt": "2024-09-01T17:56:32Z"
                    }
                },
                "canReply": true,
                "totalReplyCount": 1,
                "isPublic": true
            }
        },
        {
            "kind": "youtube#commentThread",
            "etag": "j6VM_UH658Boh-0I3JUtxe2JOLI",
            "id": "UgzY2hou7HTVEbsJWjB4AaABAg",
            "snippet": {
                "channelId": "UCXuO_AmrcE16fDoNiq9JZZg",
                "videoId": "Wm_lx5DJWZE",
                "topLevelComment": {
                    "kind": "youtube#comment",
                    "etag": "aVv1s8eNTvBBwLcaB2FGCkHhWe0",
                    "id": "UgzY2hou7HTVEbsJWjB4AaABAg",
                    "snippet": {
                        "channelId": "UCXuO_AmrcE16fDoNiq9JZZg",
                        "videoId": "Wm_lx5DJWZE",
                        "textDisplay": "Proud of you dear",
                        "textOriginal": "Proud of you dear",
                        "authorDisplayName": "@swatiuttrwar8749",
                        "authorProfileImageUrl": "https://yt3.ggpht.com/ocm2b8M29OuyXU899Z0c509Ayf6b45oi_xk-436v4E3XqjJ2wxbtaUX2n9d8luKVV2Her0cEXaE=s48-c-k-c0x00ffffff-no-rj",
                        "authorChannelUrl": "http://www.youtube.com/@swatiuttrwar8749",
                        "authorChannelId": {
                            "value": "UCVabQSXcY1OcV3WeNyXGLXQ"
                        },
                        "canRate": true,
                        "viewerRating": "none",
                        "likeCount": 0,
                        "publishedAt": "2024-09-01T08:21:11Z",
                        "updatedAt": "2024-09-01T08:21:11Z"
                    }
                },
                "canReply": true,
                "totalReplyCount": 0,
                "isPublic": true
            }
        },
        {
            "kind": "youtube#commentThread",
            "etag": "Vh37rzMvz-kax7QV3VK2t-pcVkQ",
            "id": "UgwghJi3FCC_oRcQGvJ4AaABAg",
            "snippet": {
                "channelId": "UCXuO_AmrcE16fDoNiq9JZZg",
                "videoId": "Wm_lx5DJWZE",
                "topLevelComment": {
                    "kind": "youtube#comment",
                    "etag": "i3P59E95V5JXg6UyaJmlno1j70w",
                    "id": "UgwghJi3FCC_oRcQGvJ4AaABAg",
                    "snippet": {
                        "channelId": "UCXuO_AmrcE16fDoNiq9JZZg",
                        "videoId": "Wm_lx5DJWZE",
                        "textDisplay": "Marthi kudi auperrr energetic fire \u2764\u2764\u2764\u2764",
                        "textOriginal": "Marthi kudi auperrr energetic fire \u2764\u2764\u2764\u2764",
                        "authorDisplayName": "@JitaRai-ho5sy",
                        "authorProfileImageUrl": "https://yt3.ggpht.com/ytc/AIdro_khSbcYOk-ZJpJdnM0KT63okOiFU3WwtWMvAi-S5gxJah9fOAID9GlTIjWJnSHyDKWk4A=s48-c-k-c0x00ffffff-no-rj",
                        "authorChannelUrl": "http://www.youtube.com/@JitaRai-ho5sy",
                        "authorChannelId": {
                            "value": "UC6IdbKYsQZ4XbZJmk48PjhQ"
                        },
                        "canRate": true,
                        "viewerRating": "none",
                        "likeCount": 1,
                        "publishedAt": "2024-08-31T21:04:52Z",
                        "updatedAt": "2024-08-31T21:04:52Z"
                    }
                },
                "canReply": true,
                "totalReplyCount": 1,
                "isPublic": true
            }
        },
        {
            "kind": "youtube#commentThread",
            "etag": "WBIe4NnY4hHmFxVBcRwmnvO-Nk8",
            "id": "UgzbAFzz2qU3ekdjdw14AaABAg",
            "snippet": {
                "channelId": "UCXuO_AmrcE16fDoNiq9JZZg",
                "videoId": "Wm_lx5DJWZE",
                "topLevelComment": {
                    "kind": "youtube#comment",
                    "etag": "ZtzDgcWLerE_XqrKyyV827wHWHA",
                    "id": "UgzbAFzz2qU3ekdjdw14AaABAg",
                    "snippet": {
                        "channelId": "UCXuO_AmrcE16fDoNiq9JZZg",
                        "videoId": "Wm_lx5DJWZE",
                        "textDisplay": "Srushti killed it maan \ud83d\udd25\ud83d\udd25",
                        "textOriginal": "Srushti killed it maan \ud83d\udd25\ud83d\udd25",
                        "authorDisplayName": "@shahmirworld",
                        "authorProfileImageUrl": "https://yt3.ggpht.com/l5o3Q8sLIZY76PCkJwjMpsUiSPoFzYbSUMBEbxTcUFsvViUyzzbirlzZISkznjuA7SrZj64Z=s48-c-k-c0x00ffffff-no-rj",
                        "authorChannelUrl": "http://www.youtube.com/@shahmirworld",
                        "authorChannelId": {
                            "value": "UC0SeTyhHG5p_Q8PRYr9B2Og"
                        },
                        "canRate": true,
                        "viewerRating": "none",
                        "likeCount": 0,
                        "publishedAt": "2024-08-31T12:17:01Z",
                        "updatedAt": "2024-08-31T12:17:01Z"
                    }
                },
                "canReply": true,
                "totalReplyCount": 1,
                "isPublic": true
            }
        },
        {
            "kind": "youtube#commentThread",
            "etag": "iIgovdK7Wgd9_9DLb1bt5DcUvOA",
            "id": "Ugwzg8c8LqGwajCzpCF4AaABAg",
            "snippet": {
                "channelId": "UCXuO_AmrcE16fDoNiq9JZZg",
                "videoId": "Wm_lx5DJWZE",
                "topLevelComment": {
                    "kind": "youtube#comment",
                    "etag": "TYYZH5o7CUeJl45D7FwIoXdB3Cc",
                    "id": "Ugwzg8c8LqGwajCzpCF4AaABAg",
                    "snippet": {
                        "channelId": "UCXuO_AmrcE16fDoNiq9JZZg",
                        "videoId": "Wm_lx5DJWZE",
                        "textDisplay": "Srushti di apke rep song ki fen.....+ This one \ud83d\ude03\ud83e\udd73\ud83e\udd29( fadu yar \ud83e\udd29)",
                        "textOriginal": "Srushti di apke rep song ki fen.....+ This one \ud83d\ude03\ud83e\udd73\ud83e\udd29( fadu yar \ud83e\udd29)",
                        "authorDisplayName": "@anerimachhar2172",
                        "authorProfileImageUrl": "https://yt3.ggpht.com/ytc/AIdro_kIRSmCFvDqipQkKPkdGhIkUqSKITWOdayKSC2TsHM=s48-c-k-c0x00ffffff-no-rj",
                        "authorChannelUrl": "http://www.youtube.com/@anerimachhar2172",
                        "authorChannelId": {
                            "value": "UCvElnypfMzmNN51Tdw4M8SA"
                        },
                        "canRate": true,
                        "viewerRating": "none",
                        "likeCount": 12,
                        "publishedAt": "2024-08-31T03:46:47Z",
                        "updatedAt": "2024-08-31T03:46:47Z"
                    }
                },
                "canReply": true,
                "totalReplyCount": 0,
                "isPublic": true
            }
        },
        {
            "kind": "youtube#commentThread",
            "etag": "7Xy2yg7CEAe-Fb4hsC8kBDvqNHc",
            "id": "UgwDXc66g0qI8RjrGc14AaABAg",
            "snippet": {
                "channelId": "UCXuO_AmrcE16fDoNiq9JZZg",
                "videoId": "Wm_lx5DJWZE",
                "topLevelComment": {
                    "kind": "youtube#comment",
                    "etag": "yFhAQdIJGPqHzqv7TvHezq704vM",
                    "id": "UgwDXc66g0qI8RjrGc14AaABAg",
                    "snippet": {
                        "channelId": "UCXuO_AmrcE16fDoNiq9JZZg",
                        "videoId": "Wm_lx5DJWZE",
                        "textDisplay": "Fantastic \u2764\u2764\u2764\u2764\u2764\u2764\nProud to be Maharashtrian\u2764\u2764\u2764\u2764",
                        "textOriginal": "Fantastic \u2764\u2764\u2764\u2764\u2764\u2764\nProud to be Maharashtrian\u2764\u2764\u2764\u2764",
                        "authorDisplayName": "@shravaninerkar8232",
                        "authorProfileImageUrl": "https://yt3.ggpht.com/ytc/AIdro_k9U0SeepKY-pY1DCNu6Z6AtBkW4ATDjy10UK4VPh4=s48-c-k-c0x00ffffff-no-rj",
                        "authorChannelUrl": "http://www.youtube.com/@shravaninerkar8232",
                        "authorChannelId": {
                            "value": "UCFUm29sq7eaJ8TxS4g4RnEw"
                        },
                        "canRate": true,
                        "viewerRating": "none",
                        "likeCount": 19,
                        "publishedAt": "2024-08-30T20:04:25Z",
                        "updatedAt": "2024-08-30T20:04:25Z"
                    }
                },
                "canReply": true,
                "totalReplyCount": 1,
                "isPublic": true
            }
        },
        {
            "kind": "youtube#commentThread",
            "etag": "GtlByI_Bt3K5D_gzuN4gC0Y27e0",
            "id": "UgzbjOkb2igECjtPOjZ4AaABAg",
            "snippet": {
                "channelId": "UCXuO_AmrcE16fDoNiq9JZZg",
                "videoId": "Wm_lx5DJWZE",
                "topLevelComment": {
                    "kind": "youtube#comment",
                    "etag": "7saDLDzR2C1_nyB0UAq38foHOQM",
                    "id": "UgzbjOkb2igECjtPOjZ4AaABAg",
                    "snippet": {
                        "channelId": "UCXuO_AmrcE16fDoNiq9JZZg",
                        "videoId": "Wm_lx5DJWZE",
                        "textDisplay": "\u2764\u2764\u2764\u013a",
                        "textOriginal": "\u2764\u2764\u2764\u013a",
                        "authorDisplayName": "@ChxxryRxses",
                        "authorProfileImageUrl": "https://yt3.ggpht.com/LVElW3CfeojRFLkkvQgsOXBdrHVjRb1iD0vCesq33LNyxp-rbBqvo-J0W-lnHKNqzubP6Gn5=s48-c-k-c0x00ffffff-no-rj",
                        "authorChannelUrl": "http://www.youtube.com/@ChxxryRxses",
                        "authorChannelId": {
                            "value": "UCtu-6_nwH52gMgalx1PLXgQ"
                        },
                        "canRate": true,
                        "viewerRating": "none",
                        "likeCount": 1,
                        "publishedAt": "2024-08-29T14:22:31Z",
                        "updatedAt": "2024-08-29T14:22:31Z"
                    }
                },
                "canReply": true,
                "totalReplyCount": 0,
                "isPublic": true
            }
        },
        {
            "kind": "youtube#commentThread",
            "etag": "tuf2kDjTOZ9WoSkN_JU0gwOJRvg",
            "id": "UgyVB_g9g1WaDwHZxD54AaABAg",
            "snippet": {
                "channelId": "UCXuO_AmrcE16fDoNiq9JZZg",
                "videoId": "Wm_lx5DJWZE",
                "topLevelComment": {
                    "kind": "youtube#comment",
                    "etag": "lO23CDFMtnaFcqY5iEcGkyOu-To",
                    "id": "UgyVB_g9g1WaDwHZxD54AaABAg",
                    "snippet": {
                        "channelId": "UCXuO_AmrcE16fDoNiq9JZZg",
                        "videoId": "Wm_lx5DJWZE",
                        "textDisplay": "There energy in this song is on next level \u2764\ud83d\udd25",
                        "textOriginal": "There energy in this song is on next level \u2764\ud83d\udd25",
                        "authorDisplayName": "@jiyaahirrao3285",
                        "authorProfileImageUrl": "https://yt3.ggpht.com/f4f1TkTjO_1OIdhAzFurkkA-6kp5BRuIi4oJlASo_ZyPm2Vzzseg3XlxV3_5ibcSdgAmK5zcNx0=s48-c-k-c0x00ffffff-no-rj",
                        "authorChannelUrl": "http://www.youtube.com/@jiyaahirrao3285",
                        "authorChannelId": {
                            "value": "UCfe3QVSI-3V3-hWUWk11J-A"
                        },
                        "canRate": true,
                        "viewerRating": "none",
                        "likeCount": 11,
                        "publishedAt": "2024-08-27T12:57:06Z",
                        "updatedAt": "2024-08-27T12:57:06Z"
                    }
                },
                "canReply": true,
                "totalReplyCount": 1,
                "isPublic": true
            }
        },
        {
            "kind": "youtube#commentThread",
            "etag": "W9N0oD9wzfxov3q67qwrKJasVZY",
            "id": "Ugztr9kFmnsaPS27ViR4AaABAg",
            "snippet": {
                "channelId": "UCXuO_AmrcE16fDoNiq9JZZg",
                "videoId": "Wm_lx5DJWZE",
                "topLevelComment": {
                    "kind": "youtube#comment",
                    "etag": "wktwTMJ1-6MFv4-8-gJsOpNlsMg",
                    "id": "Ugztr9kFmnsaPS27ViR4AaABAg",
                    "snippet": {
                        "channelId": "UCXuO_AmrcE16fDoNiq9JZZg",
                        "videoId": "Wm_lx5DJWZE",
                        "textDisplay": "\u2764\u2764\u2764\u2764\u2764\u2764\u2764\u2764\u2764\u2764\u2764\u2764\u2764\u2764\u2764\u2764\u2764\u2764\u2764\u2764\u2764\u2764\u2764\u2764\u2764\u2764\u2764\u2764\u2764\u2764\u2764\u2764\u2764\u2764\u2764\u2764\u2764\u2764\u2764\u2764\u2764\u2764\u2764",
                        "textOriginal": "\u2764\u2764\u2764\u2764\u2764\u2764\u2764\u2764\u2764\u2764\u2764\u2764\u2764\u2764\u2764\u2764\u2764\u2764\u2764\u2764\u2764\u2764\u2764\u2764\u2764\u2764\u2764\u2764\u2764\u2764\u2764\u2764\u2764\u2764\u2764\u2764\u2764\u2764\u2764\u2764\u2764\u2764\u2764",
                        "authorDisplayName": "@prashantbhardwaj2221",
                        "authorProfileImageUrl": "https://yt3.ggpht.com/ytc/AIdro_namH81HH1skVB_OkB7WOuuLxeN6QSWxTdJMBerCptVXfRU=s48-c-k-c0x00ffffff-no-rj",
                        "authorChannelUrl": "http://www.youtube.com/@prashantbhardwaj2221",
                        "authorChannelId": {
                            "value": "UCi5I_5NYMTAhKlmfZiK3vLw"
                        },
                        "canRate": true,
                        "viewerRating": "none",
                        "likeCount": 0,
                        "publishedAt": "2024-08-27T11:15:23Z",
                        "updatedAt": "2024-08-27T11:15:23Z"
                    }
                },
                "canReply": true,
                "totalReplyCount": 0,
                "isPublic": true
            }
        },
        {
            "kind": "youtube#commentThread",
            "etag": "i7LruadpyIzgVZjyJ_N0dpqo9Kw",
            "id": "UgwAGsnug4v0QZgBQwN4AaABAg",
            "snippet": {
                "channelId": "UCXuO_AmrcE16fDoNiq9JZZg",
                "videoId": "Wm_lx5DJWZE",
                "topLevelComment": {
                    "kind": "youtube#comment",
                    "etag": "245tf6D_y66Pi8MrKwy6G4osuGU",
                    "id": "UgwAGsnug4v0QZgBQwN4AaABAg",
                    "snippet": {
                        "channelId": "UCXuO_AmrcE16fDoNiq9JZZg",
                        "videoId": "Wm_lx5DJWZE",
                        "textDisplay": "\ud83e\udde1\ud83e\udde1\ud83d\udc9c",
                        "textOriginal": "\ud83e\udde1\ud83e\udde1\ud83d\udc9c",
                        "authorDisplayName": "@mona__92",
                        "authorProfileImageUrl": "https://yt3.ggpht.com/InMob-8fnCzU3KSKZtnDgwrBLTWgd9LcSbgB2QFLx38Vo5GZdaCbhYCGFqoowqawprSW-4v0Mw=s48-c-k-c0x00ffffff-no-rj",
                        "authorChannelUrl": "http://www.youtube.com/@mona__92",
                        "authorChannelId": {
                            "value": "UC4YctoLzbtlxloiOtQdkkHg"
                        },
                        "canRate": true,
                        "viewerRating": "none",
                        "likeCount": 3,
                        "publishedAt": "2024-08-27T09:32:53Z",
                        "updatedAt": "2024-08-27T09:32:53Z"
                    }
                },
                "canReply": true,
                "totalReplyCount": 0,
                "isPublic": true
            }
        }
    ]
}