{
    "kind": "youtube#commentThreadListResponse",
    "etag": "AXpv9WxMOrRxbeL1ixj50TSJm_U",
    "pageInfo": {
        "totalResults": 6,
        "resultsPerPage": 100
    },
    "items": [
        {
            "kind": "youtube#commentThread",
            "etag": "ktEsM7f6_6ZZ6X8UwyLezjfh6eU",
            "id": "Ugz30ne0jHBhXemXzd94AaABAg",
            "snippet": {
                "channelId": "UCIB65_E_7XEScU2NB135wDw",
                "videoId": "xvS7DVTn-Ic",
                "topLevelComment": {
                    "kind": "youtube#comment",
                    "etag": "xcXaGnP6frvBPMZ8Hos5iL-EruQ",
                    "id": "Ugz30ne0jHBhXemXzd94AaABAg",
                    "snippet": {
                        "channelId": "UCIB65_E_7XEScU2NB135wDw",
                        "videoId": "xvS7DVTn-Ic",
                        "textDisplay": "\ud83d\udc93",
                        "textOriginal": "\ud83d\udc93",
                        "authorDisplayName": "@dekapwt5618",
                        "authorProfileImageUrl": "https://yt3.ggpht.com/nizjUzy5QfTfkUC-AKLSKL0HBOIz6C3A7ePsnEMMxXChva3BpscIsAWxpkO_fdGu9gSZQ7DUGg=s48-c-k-c0x00ffffff-no-rj",
                        "authorChannelUrl": "http://www.youtube.com/@dekapwt5618",
                        "authorChannelId": {
                            "value": "UCTxObmhV_DIr47z0qyRekMg"
                        },
                        "canRate": true,
                        "viewerRating": "none",
                        "likeCount": 0,
                        "publishedAt": "2023-08-23T16:44:40Z",
                        "updatedAt": "2023-08-23T16:44:39Z"
                    }
                },
                "canReply": true,
                "totalReplyCount": 0,
                "isPublic": true
            }
        },
        {
            "kind": "youtube#commentThread",
            "etag": "q8-WFJwdVIn8-XQLCKgO-7fEtIc",
            "id": "UgyusJDZeuXlR8M8rtd4AaABAg",
            "snippet": {
                "channelId": "UCIB65_E_7XEScU2NB135wDw",
                "videoId": "xvS7DVTn-Ic",
                "topLevelComment": {
                    "kind": "youtube#comment",
                    "etag": "0KFcb3zhknJ6Bjl26is7q2CGwCU",
                    "id": "UgyusJDZeuXlR8M8rtd4AaABAg",
                    "snippet": {
                        "channelId": "UCIB65_E_7XEScU2NB135wDw",
                        "videoId": "xvS7DVTn-Ic",
                        "textDisplay": "\u2764\u2764\u2764\u2764\u2764\u2764",
                        "textOriginal": "\u2764\u2764\u2764\u2764\u2764\u2764",
                        "authorDisplayName": "@OfficialsPrinceHs",
                        "authorProfileImageUrl": "https://yt3.ggpht.com/iJpoflimjnnc3ZL13AcobL03dLSVRgNwuY2VaeOF91FbJwTnw362FFiK3TPeCtzKglwcGEU1=s48-c-k-c0x00ffffff-no-rj",
                        "authorChannelUrl": "http://www.youtube.com/@OfficialsPrinceHs",
                        "authorChannelId": {
                            "value": "UCgnduWZtg13Qwdy0iJWwZPQ"
                        },
                        "canRate": true,
                        "viewerRating": "none",
                        "likeCount": 0,
                        "publishedAt": "2023-07-29T11:13:20Z",
                        "updatedAt": "2023-07-29T11:13:20Z"
                    }
                },
                "canReply": true,
                "totalReplyCount": 0,
                "isPublic": true
            }
        },
        {
            "kind": "youtube#commentThread",
            "etag": "23wAu2QDtxP-HiJkCrn4Eo34fYw",
            "id": "UgzE-kxswMnAEkWoilx4AaABAg",
            "snippet": {
                "channelId": "UCIB65_E_7XEScU2NB135wDw",
                "videoId": "xvS7DVTn-Ic",
                "topLevelComment": {
                    "kind": "youtube#comment",
                    "etag": "W1BCejl2X6xLr8Y4N-XKWN_CYhE",
                    "id": "UgzE-kxswMnAEkWoilx4AaABAg",
                    "snippet": {
                        "channelId": "UCIB65_E_7XEScU2NB135wDw",
                        "videoId": "xvS7DVTn-Ic",
                        "textDisplay": "\ud83e\udd70",
                        "textOriginal": "\ud83e\udd70",
                        "authorDisplayName": "@mdhamimpk",
                        "authorProfileImageUrl": "https://yt3.ggpht.com/ytc/AIdro_nZa2L5tvX7AvSd4Ge5CNES4grhI0iSwAR0FOEKVgy-ONyNf84-qq6U12ADeVbgPcot_Q=s48-c-k-c0x00ffffff-no-rj",
                        "authorChannelUrl": "http://www.youtube.com/@mdhamimpk",
                        "authorChannelId": {
                            "value": "UCnEcxR_lt_M_F8b-zmr6qzQ"
                        },
                        "canRate": true,
                        "viewerRating": "none",
                        "likeCount": 0,
                        "publishedAt": "2023-07-26T09:13:11Z",
                        "updatedAt": "2023-07-26T09:13:11Z"
                    }
                },
                "canReply": true,
                "totalReplyCount": 0,
                "isPublic": true
            }
        },
        {
            "kind": "youtube#commentThread",
            "etag": "pNkQ8OyNQIjeXze3DpCcjg7Pv-8",
            "id": "UgwJRpXBs_gcvAnkez14AaABAg",
            "snippet": {
                "channelId": "UCIB65_E_7XEScU2NB135wDw",
                "videoId": "xvS7DVTn-Ic",
                "topLevelComment": {
                    "kind": "youtube#comment",
                    "etag": "7hR9sgFvMPwjNgtaJ58NhqbJhEM",
                    "id": "UgwJRpXBs_gcvAnkez14AaABAg",
                    "snippet": {
                        "channelId": "UCIB65_E_7XEScU2NB135wDw",
                        "videoId": "xvS7DVTn-Ic",
                        "textDisplay": "\ud83e\udd70\ud83e\udd70\ud83e\udd70",
                        "textOriginal": "\ud83e\udd70\ud83e\udd70\ud83e\udd70",
                        "authorDisplayName": "@JOY-vi7oc",
                        "authorProfileImageUrl": "https://yt3.ggpht.com/yUtwdFYgx7uahZdjEnNmQlHS3AQIfaq7BV7SCY2MeFLV-TlggXjJHRj65aC_4tgaDDU2v58O4w=s48-c-k-c0x00ffffff-no-rj",
                        "authorChannelUrl": "http://www.youtube.com/@JOY-vi7oc",
                        "authorChannelId": {
                            "value": "UCL6X5GC95qz9BHrUZfRLPFw"
                        },
                        "canRate": true,
                        "viewerRating": "none",
                        "likeCount": 0,
                        "publishedAt": "2023-07-25T19:24:57Z",
                        "updatedAt": "2023-07-25T19:24:57Z"
                    }
                },
                "canReply": true,
                "totalReplyCount": 0,
                "isPublic": true
            }
        },
        {
            "kind": "youtube#commentThread",
            "etag": "zWs0_txMsynjfI9SvLFE7hMJVe0",
            "id": "UgzVKSxu1X4CMM_hQfp4AaABAg",
            "snippet": {
                "channelId": "UCIB65_E_7XEScU2NB135wDw",
                "videoId": "xvS7DVTn-Ic",
                "topLevelComment": {
                    "kind": "youtube#comment",
                    "etag": "_ICaBBpBGA8HqTpRs9ZMmCLjMvI",
                    "id": "UgzVKSxu1X4CMM_hQfp4AaABAg",
                    "snippet": {
                        "channelId": "UCIB65_E_7XEScU2NB135wDw",
                        "videoId": "xvS7DVTn-Ic",
                        "textDisplay": "\ud83d\ude2e\ud83d\ude2e\ud83d\ude2e\ud83d\ude2e\ud83d\ude2e",
                        "textOriginal": "\ud83d\ude2e\ud83d\ude2e\ud83d\ude2e\ud83d\ude2e\ud83d\ude2e",
                        "authorDisplayName": "@mrallrounder8701",
                        "authorProfileImageUrl": "https://yt3.ggpht.com/PQnxUK_730vRjMYZZCx8b21n0Dq_H4OsNqviskl5laImHNCMXrWqAA_LhYPJ1KLgPQ7UnJOQtpU=s48-c-k-c0x00ffffff-no-rj",
                        "authorChannelUrl": "http://www.youtube.com/@mrallrounder8701",
                        "authorChannelId": {
                            "value": "UC4wZjg5QZK6c8IJr7oWl4XA"
                        },
                        "canRate": true,
                        "viewerRating": "none",
                        "likeCount": 0,
                        "publishedAt": "2023-07-25T15:49:55Z",
                        "updatedAt": "2023-07-25T15:49:55Z"
                    }
                },
                "canReply": true,
                "totalReplyCount": 0,
                "isPublic": true
            }
        },
        {
            "kind": "youtube#commentThread",
            "etag": "7M_p4hdgvZPYq2m8qvPslHBUzDo",
            "id": "UgzEcpT5xsfdI1_8fu54AaABAg",
            "snippet": {
                "channelId": "UCIB65_E_7XEScU2NB135wDw",
                "videoId": "xvS7DVTn-Ic",
                "topLevelComment": {
                    "kind": "youtube#comment",
                    "etag": "RumBGMYUOElt34LcW3jsYANL0ps",
                    "id": "UgzEcpT5xsfdI1_8fu54AaABAg",
                    "snippet": {
                        "channelId": "UCIB65_E_7XEScU2NB135wDw",
                        "videoId": "xvS7DVTn-Ic",
                        "textDisplay": "Nice",
                        "textOriginal": "Nice",
                        "authorDisplayName": "@MdSohan-yb2yo",
                        "authorProfileImageUrl": "https://yt3.ggpht.com/KI6Tm3Q89b9eYHtRsh9-yj2gzzrtgQiNakuNv2o07bgZ2B8UnkddfHZt1rn16bZoX5HnH6tXWw=s48-c-k-c0x00ffffff-no-rj",
                        "authorChannelUrl": "http://www.youtube.com/@MdSohan-yb2yo",
                        "authorChannelId": {
                            "value": "UCoOz6sb-H-igevTJ4IZYe4Q"
                        },
                        "canRate": true,
                        "viewerRating": "none",
                        "likeCount": 1,
                        "publishedAt": "2023-07-25T15:21:20Z",
                        "updatedAt": "2023-07-25T15:21:20Z"
                    }
                },
                "canReply": true,
                "totalReplyCount": 0,
                "isPublic": true
            }
        }
    ]
}